hybra/__init__.py
hybra/_fit_dual.py
hybra/hybridfilterbank.py
hybra/isac.py
hybra/isac_mel.py
hybra/isac_mfcc.py
hybra/utils.py
hybra-2025.9.5.dist-info/licenses/LICENSE
hybra-2025.9.5.dist-info/METADATA
hybra-2025.9.5.dist-info/WHEEL
hybra-2025.9.5.dist-info/top_level.txt
hybra-2025.9.5.dist-info/RECORD
