Metadata-Version: 2.4
Name: hybra
Version: 2025.9.5
Summary: A module for trainable encoder/decoder filterbanks with auditory bias.
Author: Daniel Haider and Felix Perfler
Project-URL: Repository, https://github.com/danedane-haider/Hybrid-Auditory-Filterbanks.git
Keywords: filterbank,filterbank learning,feature extraction,hybrid filterbanks,encoder,decoder,auditory,frames,audio front-end,audio,machine-learning,pytorch,speech,music,⛷️
Classifier: Programming Language :: Python
Requires-Python: >=3.9
License-File: LICENSE
Requires-Dist: matplotlib
Requires-Dist: numpy
Requires-Dist: torch
Dynamic: license-file
